pytest_resource_usage/__init__.py
pytest_resource_usage/duration.py
pytest_resource_usage/psutil_uss.py
pytest_resource_usage/report.py
pytest_resource_usage/tracemalloc.py
pytest_resource_usage/uss.py
pytest_resource_usage-1.0.0.dist-info/entry_points.txt
pytest_resource_usage-1.0.0.dist-info/LICENSE
pytest_resource_usage-1.0.0.dist-info/WHEEL
pytest_resource_usage-1.0.0.dist-info/METADATA
pytest_resource_usage-1.0.0.dist-info/RECORD
