Metadata-Version: 2.1
Name: pytest-resource-usage
Version: 1.0.0
Summary: Pytest plugin for reporting running time and peak memory usage
Author-email: Jouke Witteveen <j.witteveen@gmail.com>
Requires-Python: >=3.8
Classifier: Development Status :: 5 - Production/Stable
Classifier: Framework :: Pytest
Classifier: Intended Audience :: Developers
Classifier: License :: OSI Approved :: MIT License
Classifier: Operating System :: OS Independent
Classifier: Programming Language :: Python :: 3
Classifier: Topic :: Software Development :: Testing
Requires-Dist: pytest>=7.0.0
Requires-Dist: psutil>=4.0.0 ; extra == "report_uss"
Project-URL: Bug Tracker, https://github.com/joukewitteveen/pytest-resource-usage/issues
Project-URL: Homepage, https://github.com/joukewitteveen/pytest-resource-usage
Provides-Extra: report_uss
